odoo/addons/hr_timesheet_calendar/README.rst
odoo/addons/hr_timesheet_calendar/__init__.py
odoo/addons/hr_timesheet_calendar/__manifest__.py
odoo/addons/hr_timesheet_calendar/i18n/hr_timesheet_calendar.pot
odoo/addons/hr_timesheet_calendar/i18n/it.po
odoo/addons/hr_timesheet_calendar/models/__init__.py
odoo/addons/hr_timesheet_calendar/models/account_analytic_line.py
odoo/addons/hr_timesheet_calendar/models/res_config_settings.py
odoo/addons/hr_timesheet_calendar/readme/CONTRIBUTORS.md
odoo/addons/hr_timesheet_calendar/readme/DESCRIPTION.md
odoo/addons/hr_timesheet_calendar/static/description/icon.png
odoo/addons/hr_timesheet_calendar/static/description/icon.svg
odoo/addons/hr_timesheet_calendar/static/description/index.html
odoo/addons/hr_timesheet_calendar/static/src/views/timesheet_calendar/timesheet_calendar_controller.esm.js
odoo/addons/hr_timesheet_calendar/static/src/views/timesheet_calendar/timesheet_calendar_renderer.esm.js
odoo/addons/hr_timesheet_calendar/static/src/views/timesheet_calendar/timesheet_calendar_view.esm.js
odoo/addons/hr_timesheet_calendar/static/src/views/timesheet_calendar/common/timesheet_calendar_common_popover.esm.js
odoo/addons/hr_timesheet_calendar/static/src/views/timesheet_calendar/common/timesheet_calendar_common_popover.xml
odoo/addons/hr_timesheet_calendar/static/src/views/timesheet_calendar/common/timesheet_calendar_common_renderer.esm.js
odoo/addons/hr_timesheet_calendar/tests/__init__.py
odoo/addons/hr_timesheet_calendar/tests/test_account_analytic_line.py
odoo/addons/hr_timesheet_calendar/views/hr_timesheet_views.xml
odoo/addons/hr_timesheet_calendar/views/res_config_settings_view.xml
odoo_addon_hr_timesheet_calendar-18.0.1.1.0.dist-info/METADATA
odoo_addon_hr_timesheet_calendar-18.0.1.1.0.dist-info/WHEEL
odoo_addon_hr_timesheet_calendar-18.0.1.1.0.dist-info/top_level.txt
odoo_addon_hr_timesheet_calendar-18.0.1.1.0.dist-info/RECORD
