Metadata-Version: 2.1
Name: odoo-addon-hr_timesheet_calendar
Version: 18.0.1.1.0
Requires-Python: >=3.10
Requires-Dist: odoo-addon-project_timesheet_time_control==18.0.*
Requires-Dist: odoo==18.0.*
Summary: HR Timesheet Calendar
Home-page: https://github.com/OCA/timesheet
License: AGPL-3
Author: Lansana Barry Sow, APSL-Nagarro, Odoo Community Association (OCA)
Author-email: support@odoo-community.org
Classifier: Programming Language :: Python
Classifier: Framework :: Odoo
Classifier: Framework :: Odoo :: 18.0
Classifier: License :: OSI Approved :: GNU Affero General Public License v3
